agrograph_processing_toolbox/__init__.py
agrograph_processing_toolbox/main.py
agrograph_processing_toolbox-0.0.1.dist-info/LICENSE
agrograph_processing_toolbox-0.0.1.dist-info/METADATA
agrograph_processing_toolbox-0.0.1.dist-info/WHEEL
agrograph_processing_toolbox-0.0.1.dist-info/top_level.txt
agrograph_processing_toolbox-0.0.1.dist-info/RECORD
