Metadata-Version: 2.1
Name: agrograph-processing-toolbox
Version: 0.0.1
Summary: Package containing a collection of scripts to switch between postgres and pandas
Home-page: https://github.com/pypa/sampleproject
Author: Matt Bougie
Author-email: matt@agrograph.com
License: UNKNOWN
Project-URL: Bug Tracker, https://github.com/pypa/sampleproject/issues
Platform: UNKNOWN
Classifier: Programming Language :: Python :: 3
Classifier: License :: OSI Approved :: MIT License
Classifier: Operating System :: OS Independent
Requires-Python: >=3.6
License-File: LICENSE
